d1_doc/Makefile
d1_doc/__init__.py
d1_doc/build-all.py
d1_doc/gen-command-help.py
dataone.doc-3.5.1.dist-info/METADATA
dataone.doc-3.5.1.dist-info/WHEEL
dataone.doc-3.5.1.dist-info/top_level.txt
dataone.doc-3.5.1.dist-info/RECORD
